Metadata-Version: 1.1
Name: coptictranslit
Version: 0.1.2
Summary: An inital release of a Coptic Transliterator
Home-page: https://github.com/shehatamichael/coptic-transliteration
Author: Michael Shehata
Author-email: shehatamichael4@gmail.com
License: UNKNOWN
Keywords: Coptic
Platform: UNKNOWN
Classifier: License :: OSI Approved :: MIT License
Classifier: Programming Language :: Python :: 3
Classifier: Programming Language :: Python :: 3.3
Classifier: Programming Language :: Python :: 3.4
Classifier: Programming Language :: Python :: 3.5
Classifier: Programming Language :: Python :: 3.6
Classifier: Programming Language :: Python :: 3.7
